kogitune/__init__.py
kogitune/cli.py
kogitune/commons.py
kogitune/composers.py
kogitune/da.py
kogitune/evaluators.py
kogitune/file_utils.py
kogitune/pttokenizer.py
kogitune/scratch.py
kogitune/splitters.py
kogitune/t5trainers.py
kogitune/tokenizers.py
kogitune/trainers.py
kogitune-0.1.dist-info/LICENSE
kogitune-0.1.dist-info/METADATA
kogitune-0.1.dist-info/WHEEL
kogitune-0.1.dist-info/entry_points.txt
kogitune-0.1.dist-info/top_level.txt
kogitune-0.1.dist-info/RECORD
