Metadata-Version: 2.1
Name: kogitune
Version: 0.1
Summary: The Kogitune 🦊 LLM Project
Home-page: https://github.com/kuramitsulab/kogitune
Author: Kimio Kuramitsu
License: Apache
Platform: UNKNOWN
Classifier: Development Status :: 4 - Beta
Classifier: License :: OSI Approved :: Apache Software License
Classifier: Programming Language :: Python :: 3.7
Classifier: Programming Language :: Python :: 3.8
Classifier: Programming Language :: Python :: 3.9
Classifier: Programming Language :: Python :: 3.10
Classifier: Intended Audience :: Education
License-File: LICENSE
Requires-Dist: torch (>=2.0.0)
Requires-Dist: sentencepiece
Requires-Dist: transformers (>=4.27.0)
Requires-Dist: datasets (>=2.11.0)
Requires-Dist: accelerate
Requires-Dist: nvidia-ml-py3
Requires-Dist: bitsandbytes
Requires-Dist: deepspeed
Requires-Dist: sacrebleu
Requires-Dist: evaluate
Requires-Dist: pyzstd
